django_mkdocs/__init__.py
django_mkdocs/app_settings.py
django_mkdocs/tests.py
django_mkdocs/urls.py
django_mkdocs/views.py
django_mkdocs_updated-0.1.6.dist-info/LICENSE
django_mkdocs_updated-0.1.6.dist-info/METADATA
django_mkdocs_updated-0.1.6.dist-info/WHEEL
django_mkdocs_updated-0.1.6.dist-info/top_level.txt
django_mkdocs_updated-0.1.6.dist-info/RECORD
