Metadata-Version: 2.1
Name: django-mkdocs-updated
Version: 0.1.6
Summary: MkDocs served by Django for permissioned access
Author: Ali moradi
Author-email: ali.mrd318@gmail.com
License: LGPL
Platform: UNKNOWN
Classifier: Environment :: Web Environment
Classifier: Framework :: Django :: 3
Classifier: Intended Audience :: Developers
Classifier: License :: OSI Approved :: BSD License
Classifier: Operating System :: OS Independent
Classifier: Programming Language :: Python :: 3
Classifier: Topic :: Internet :: WWW/HTTP
Classifier: Topic :: Internet :: WWW/HTTP :: Dynamic Content
Requires-Python: >=3.1
License-File: LICENSE
Requires-Dist: mkdocs
